Workbook

Sheet Resumo
A1: MAYA — Unit Economics & Pricing
A2: Edite apenas as células amarelas (e o dropdown). Azul/verde = fórmulas, recalculam sozinhas. Valores em USD.
A4: ENTRADAS — edite aqui
A5: Preço mensal (USD) | B5: 9.99
A6: Preço anual (USD) | B6: 83.99
A7: Dias de trial grátis | B7: 7
A8: Canal de cobrança | B8: Web (Stripe)
A9: Taxa de pagamento (%) | B9: =IF(B8="Web (Stripe)",0.029,IF(B8="App Store/Play - 30%",0.3,0.15))
A10: Taxa fixa por cobrança (USD) | B10: =IF(B8="Web (Stripe)",0.3,0)
A11: Churn mensal (%) | B11: 0.1
A12: Custo IA / usuário / mês (USD) | B12: =Custos!B22
A13: Custo infra / usuário / mês (USD) | B13: =Custos!B23
A14: CPI — custo por instalação (USD) | B14: 2
A15: Conversão signup → assinante (%) | B15: 0.1
A16: Web (Stripe) = 2,9% + US$0,30 • Loja 30% = padrão Apple 1º ano • Loja 15% = Google assinatura / Apple Small Business (<US$1M) / 2º ano. No app nativo a loja SUBSTITUI o Stripe.
A17: RESULTADOS
A18: Lucro bruto mensal (USD) | B18: =B5*(1-B9)-B10-B12-B13
A19: Margem bruta mensal (%) | B19: =B18/B5
A20: Lucro bruto anual (USD) | B20: =B6*(1-B9)-B10-(B12+B13)*12
A21: Margem bruta anual (%) | B21: =B20/B6
A22: LTV — lucro bruto (USD) | B22: =B18/B11
A23: CAC real (USD) | B23: =B14/B15
A24: LTV : CAC | B24: =B22/B23
A25: Payback (meses) | B25: =B23/B18
A26: LTV:CAC ≥ 3x é o saudável. Mesmo a 30% de taxa de loja o app segue lucrativo (2,3x); a 15% fica em ~3x.
A28: LUCRO LÍQUIDO (visão do negócio — preencha suas despesas)
A29: Assinantes ativos | B29: 100
A30: Despesas fixas/mês (USD) | B30: 200
A31: Verba de anúncios/mês (USD) | B31: 0
A32: Receita bruta/mês (USD) | B32: =B29*B5
A33: Lucro bruto total/mês (USD) | B33: =B29*B18
A34: Lucro LÍQUIDO/mês (USD) | B34: =B33-B30-B31
A35: Margem líquida (%) | B35: =B34/B32
A36: Lucro bruto = sobra por usuário após IA+infra+taxa. Líquido = bruto total − despesas fixas − anúncios. No começo o líquido pode ficar negativo (você compra crescimento); o equilíbrio vem com escala.

Sheet Custos
A1: Custo de IA por usuário ativo (mensal)
A2: Modelos: Haiku 4.5 = $1/M in / $5/M out • Sonnet 5 = $3/M in / $15/M out (tarifa padrão, após 31/08/2026). • Voz: ElevenLabs Turbo v2.5 = US$0,05/1k chars • Deepgram Nova-3 = US$0,0077/min (streaming).
A4: Preço por milhão de tokens (USD)
A5: Modelo | B5: Input/M | C5: Output/M
A6: Haiku 4.5 | B6: 1 | C6: 5
A7: Sonnet 5 | B7: 3 | C7: 15
A9: Chamada LLM | B9: Modelo | C9: Tokens in | D9: Tokens out | E9: Chamadas/mês | F9: Custo/mês (USD) | G9: Nota
A10: Especialistas (8x batch) | B10: Haiku 4.5 | C10: 3000 | D10: 350 | E10: 240 | F10: =E10*(C10/1000000*VLOOKUP(B10,$A$6:$C$7,2,0)+D10/1000000*VLOOKUP(B10,$A$6:$C$7,3,0)) | G10: Dispara a cada check-in (8 esp. × ~30 check-ins)
A11: Mensagem da home | B11: Haiku 4.5 | C11: 3000 | D11: 150 | E11: 30 | F11: =E11*(C11/1000000*VLOOKUP(B11,$A$6:$C$7,2,0)+D11/1000000*VLOOKUP(B11,$A$6:$C$7,3,0)) | G11: Cache 1x/dia
A12: Nudge | B12: Haiku 4.5 | C12: 3000 | D12: 120 | E12: 15 | F12: =E12*(C12/1000000*VLOOKUP(B12,$A$6:$C$7,2,0)+D12/1000000*VLOOKUP(B12,$A$6:$C$7,3,0)) | G12: Cache/dia; pula se já conversou
A13: Chat Maya | B13: Haiku 4.5 | C13: 3000 | D13: 400 | E13: 60 | F13: =E13*(C13/1000000*VLOOKUP(B13,$A$6:$C$7,2,0)+D13/1000000*VLOOKUP(B13,$A$6:$C$7,3,0)) | G13: Por mensagem enviada
A14: Extração de fatos (chat) | B14: Haiku 4.5 | C14: 1000 | D14: 150 | E14: 60 | F14: =E14*(C14/1000000*VLOOKUP(B14,$A$6:$C$7,2,0)+D14/1000000*VLOOKUP(B14,$A$6:$C$7,3,0)) | G14: Fire-and-forget por mensagem
A15: Foto de refeição | B15: Sonnet 5 | C15: 1500 | D15: 2000 | E15: 12 | F15: =E15*(C15/1000000*VLOOKUP(B15,$A$6:$C$7,2,0)+D15/1000000*VLOOKUP(B15,$A$6:$C$7,3,0)) | G15: Visão; resolução maior
A16: Recibo (finanças) | B16: Haiku 4.5 | C16: 1500 | D16: 1200 | E16: 4 | F16: =E16*(C16/1000000*VLOOKUP(B16,$A$6:$C$7,2,0)+D16/1000000*VLOOKUP(B16,$A$6:$C$7,3,0)) | G16: Visão
A17: Chats nutrição/metas/plano | B17: Haiku 4.5 | C17: 2000 | D17: 500 | E17: 15 | F17: =E17*(C17/1000000*VLOOKUP(B17,$A$6:$C$7,2,0)+D17/1000000*VLOOKUP(B17,$A$6:$C$7,3,0)) | G17: Sob demanda
A18: Reflexão semanal | B18: Haiku 4.5 | C18: 2500 | D18: 600 | E18: 4 | F18: =E18*(C18/1000000*VLOOKUP(B18,$A$6:$C$7,2,0)+D18/1000000*VLOOKUP(B18,$A$6:$C$7,3,0)) | G18: 1x/semana
A19: Reflexão mensal | B19: Haiku 4.5 | C19: 3000 | D19: 500 | E19: 1 | F19: =E19*(C19/1000000*VLOOKUP(B19,$A$6:$C$7,2,0)+D19/1000000*VLOOKUP(B19,$A$6:$C$7,3,0)) | G19: 1x/mês
A20: TTS — voz da Maya | B20: ElevenLabs Turbo v2.5 | C20: 400 | E20: 40 | F20: =E20*C20/1000*0.05 | G20: US$0,05/1k chars; ~400 chars/resposta
A21: STT — transcrição de voz | B21: Deepgram Nova-3 | C21: 15 | E21: 40 | F21: =E21*C21/60*0.0077 | G21: US$0,0077/min (streaming); ~15s/áudio
A22: TOTAL IA (LLM + voz) / usuário / mês (USD) | B22: =SUM(F10:F21)
A23: Infra fixa (Supabase/Vercel/Mapbox/push) / mês (USD) | B23: 0.1
A24: COGS TOTAL / usuário / mês (USD) | B24: =B22+B23
A26: Cenários (edite a coluna 'Chamadas/mês'): usuário casual ~US$0,50-1,50 • médio ~US$2-3 • power user ~US$5-8 • voz adiciona ~US$0,50-1,00 (médio).

Sheet Trafego_CAC
A1: Tráfego pago — CAC, LTV e ROAS
A2: Benchmarks Meta Ads 2026 (BR/CL). Ajuste as células amarelas.
A4: FUNIL & CAC
A5: CPI — custo por instalação (USD) | B5: =Resumo!B14
A6: Conversão signup → assinante (%) | B6: =Resumo!B15
A7: CAC — custo por assinante (USD) | B7: =B5/B6
A8: Lucro bruto mensal (USD) | B8: =Resumo!B18
A9: Churn mensal (%) | B9: =Resumo!B11
A10: LTV — lucro bruto (USD) | B10: =B8/B9
A11: LTV : CAC | B11: =B10/B7
A12: Payback (meses) | B12: =B7/B8
A14: SIMULAÇÃO DE ORÇAMENTO
A15: Orçamento diário (USD) | B15: 30
A16: Instalações / dia | B16: =B15/B5
A17: Assinantes / dia | B17: =B16*B6
A18: Assinantes / mês | B18: =B17*30
A19: Gasto total / mês (USD) | B19: =B15*30
A20: Receita bruta nova / mês (USD) | B20: =B18*Resumo!B5
A21: ROAS do 1º mês | B21: =B20/B19
A23: Recomendação: começar com US$20-30/dia, 2-4 criativos (BR e CL separados). Escalar só os conjuntos com CAC ≤ US$20.

Sheet Sociedade
A1: SOCIEDADE — Maya (Letierre & Weliton)
A2: Valores em R$ (BRL). Edite as células amarelas. Verde = fórmulas (recalculam sozinhas).
A3: Regra: Weliton recebe 25% da receita bruta de até 100 assinantes ativos simultâneos; Letierre fica com o restante (75% dos 100 + 100% do que passar de 100).
A5: ENTRADAS — edite aqui
A6: Preço mensal (R$) | B6: 49.9
A7: Preço anual (R$) | B7: 399.9
A8: % de assinantes mensais (resto = anual) | B8: 0.8
A9: % do Weliton | B9: 0.25
A10: Teto de assinantes simultâneos | B10: 100
A11: Assinantes ativos agora | B11: 0
A13: RESULTADO — mês atual
A14: Preço médio / assinante / mês (R$) | B14: =B6*B8+B7/12*(1-B8)
A15: Receita mensal dos ativos (R$) | B15: =B11*B14
A16: Receita dentro do teto (até 100) | B16: =MIN(B11,B10)*B14
A17: Weliton recebe / mês (R$) | B17: =B9*B16
A18: Letierre recebe / mês (R$) | B18: =B15-B17
A20: CENÁRIOS — por nº de assinantes ativos simultâneos
A21: Assinantes | B21: Receita total (R$) | C21: Weliton (R$) | D21: Letierre (R$)
A22: 50 | B22: =A22*$B$14 | C22: =$B$9*MIN(A22,$B$10)*$B$14 | D22: =B22-C22
A23: 100 | B23: =A23*$B$14 | C23: =$B$9*MIN(A23,$B$10)*$B$14 | D23: =B23-C23
A24: 150 | B24: =A24*$B$14 | C24: =$B$9*MIN(A24,$B$10)*$B$14 | D24: =B24-C24
A25: 300 | B25: =A25*$B$14 | C25: =$B$9*MIN(A25,$B$10)*$B$14 | D25: =B25-C25
A26: Acima de 100 ativos, o Weliton fica constante e todo o excedente vai para o Letierre.
A27: Teto de 12 meses por assinante: mensal = 25% por até 12 parcelas; anual = 25% do pagamento único (renovação do 2º ano não conta).
